dpmhalo/__init__.py
dpmhalo/darkmatter.py
dpmhalo/data.py
dpmhalo/emissiontab.py
dpmhalo/gaussian.py
dpmhalo/iontab.py
dpmhalo/lookuptables.py
dpmhalo/modelparams.py
dpmhalo/modelprofiles.py
dpmhalo/myconstants.py
dpmhalo/myutils.py
dpmhalo/smhm.py
dpmhalo/Data/Bregman_2022-updated.LStar_stack.dat
dpmhalo/Data/Ghizzardi_2021.Cluster_Z.dat
dpmhalo/Data/LogU_table.nullfilled.csv
dpmhalo/Data/Lovisari2015.ne_groups.dat
dpmhalo/Data/Lovisari_2019.Groups_Z.dat
dpmhalo/Data/McDonald_2017.rhocrit_r500.dat
dpmhalo/Data/NoN891_wbs_radial_shiftedBetaP2020_bootstrap_Jan2021.txt
dpmhalo/Data/Pratt_2021.groups_stack.dat
dpmhalo/Data/Prochaska_2017.COS-Halos.dat
dpmhalo/Data/Sun2009_density.groups.dat
dpmhalo/Data/Sun2011_normalizedpressure.clusters.dat
dpmhalo/Data/Sun2011_normalizedpressure.groups.dat
dpmhalo/Data/Tchernyshyov_2022.Table3.tsv
dpmhalo/Data/WuMcQuinn_2023.FRB.dat
dpmhalo/Data/XGAP_median_Fe_profiles.dat
dpmhalo/Data/XGAP_median_profiles.dat
dpmhalo/Data/Zhang2024b_Table3.txt
dpmhalo/Data/profile_CENhalo_CGM_XRB_2M31.txt
dpmhalo/Data/profile_CENhalo_CGM_XRB_4M31.txt
dpmhalo/Data/profile_CENhalo_CGM_XRB_M31.txt
dpmhalo/Data/profile_CENhalo_CGM_XRB_MW.txt
dpmhalo/Data/profile_CENhalo_CGM_XRB_hMW.txt
dpmhalo/Data/Behroozi_UNIVERSEMACHINE/SMHM_med_cen.z0.0.txt
dpmhalo/Data/Behroozi_UNIVERSEMACHINE/SMHM_med_cen.z0.1.txt
dpmhalo/Data/Behroozi_UNIVERSEMACHINE/SMHM_med_cen.z0.2.txt
dpmhalo/Data/Behroozi_UNIVERSEMACHINE/SMHM_med_cen.z0.3.txt
dpmhalo/Data/Behroozi_UNIVERSEMACHINE/SMHM_med_cen.z0.4.txt
dpmhalo/Data/Behroozi_UNIVERSEMACHINE/SMHM_med_cen.z0.5.txt
dpmhalo/Data/Behroozi_UNIVERSEMACHINE/SMHM_med_cen.z0.6.txt
dpmhalo/Data/Behroozi_UNIVERSEMACHINE/SMHM_med_cen.z0.7.txt
dpmhalo/Data/Behroozi_UNIVERSEMACHINE/SMHM_med_cen.z0.8.txt
dpmhalo/Data/Behroozi_UNIVERSEMACHINE/SMHM_med_cen.z0.9.txt
dpmhalo/Data/Behroozi_UNIVERSEMACHINE/SMHM_med_cen.z1.0.txt
dpmhalo/Data/Behroozi_UNIVERSEMACHINE/SMHM_med_cen_q.z0.0.txt
dpmhalo-1.2.dist-info/LICENSE
dpmhalo-1.2.dist-info/METADATA
dpmhalo-1.2.dist-info/WHEEL
dpmhalo-1.2.dist-info/top_level.txt
dpmhalo-1.2.dist-info/RECORD
